drstorage/__init__.py
drstorage/version.py
drstorage/cli/__init__.py
drstorage/cli/cli.py
drstorage/models/__init__.py
drstorage/models/base.py
drstorage/models/f1.py
drstorage/models/x2m.py
drstorage-0.2.2.dist-info/LICENSE
drstorage-0.2.2.dist-info/METADATA
drstorage-0.2.2.dist-info/WHEEL
drstorage-0.2.2.dist-info/entry_points.txt
drstorage-0.2.2.dist-info/top_level.txt
drstorage-0.2.2.dist-info/RECORD
