Metadata-Version: 2.1
Name: drstorage
Version: 0.2.2
Summary: Protocol Parser for Dr. Storage Dry Air Cabinets
Home-page: https://github.com/kratsg/drstorage
Author: Giordon Stark
Author-email: gstark@cern.ch
License: BSD 3-Clause
Project-URL: Documentation, https://kratsg.github.io/drstorage/
Project-URL: Source, https://github.com/kratsg/drstorage
Project-URL: Tracker, https://github.com/kratsg/drstorage/issues
Keywords: hep utilities physics protocol struct drstorage dry air cabinet
Platform: UNKNOWN
Classifier: Development Status :: 3 - Alpha
Classifier: License :: OSI Approved :: Apache Software License
Classifier: Intended Audience :: Science/Research
Classifier: Topic :: Scientific/Engineering
Classifier: Topic :: Scientific/Engineering :: Interface Engine/Protocol Translator
Classifier: Topic :: Scientific/Engineering :: Physics
Classifier: Topic :: System :: Hardware
Classifier: Programming Language :: Python :: 3
Classifier: Programming Language :: Python :: 3.6
Classifier: Programming Language :: Python :: 3.7
Classifier: Programming Language :: Python :: 3.8
Classifier: Topic :: Utilities
Requires-Python: >=3.6
Requires-Dist: click (>=7.0)
Requires-Dist: construct (>=2.10)
Provides-Extra: complete
Requires-Dist: black ; extra == 'complete'
Requires-Dist: bump2version ; extra == 'complete'
Requires-Dist: check-manifest ; extra == 'complete'
Requires-Dist: flake8 ; extra == 'complete'
Requires-Dist: pre-commit ; extra == 'complete'
Requires-Dist: pytest-console-scripts (~=0.2) ; extra == 'complete'
Requires-Dist: pytest-cov (~=2.8) ; extra == 'complete'
Requires-Dist: pytest-mock (~=3.0) ; extra == 'complete'
Requires-Dist: pytest (~=6.0) ; extra == 'complete'
Requires-Dist: twine ; extra == 'complete'
Provides-Extra: develop
Requires-Dist: black ; extra == 'develop'
Requires-Dist: bump2version ; extra == 'develop'
Requires-Dist: check-manifest ; extra == 'develop'
Requires-Dist: flake8 ; extra == 'develop'
Requires-Dist: pre-commit ; extra == 'develop'
Requires-Dist: pytest-console-scripts (~=0.2) ; extra == 'develop'
Requires-Dist: pytest-cov (~=2.8) ; extra == 'develop'
Requires-Dist: pytest-mock (~=3.0) ; extra == 'develop'
Requires-Dist: pytest (~=6.0) ; extra == 'develop'
Requires-Dist: twine ; extra == 'develop'
Provides-Extra: lint
Requires-Dist: black ; extra == 'lint'
Requires-Dist: flake8 ; extra == 'lint'
Provides-Extra: test
Requires-Dist: check-manifest ; extra == 'test'
Requires-Dist: pytest-console-scripts (~=0.2) ; extra == 'test'
Requires-Dist: pytest-cov (~=2.8) ; extra == 'test'
Requires-Dist: pytest-mock (~=3.0) ; extra == 'test'
Requires-Dist: pytest (~=6.0) ; extra == 'test'
